clean/__init__.py
clean/add.py
clean/cli.py
clean/config.py
clean/cwd.py
clean/delete.py
clean/list.py
clean/move.py
clean/pathutil.py
clean/updates/__init__.py
clean/updates/updator.py
clean/updates/versions/__init__.py
clean/updates/versions/v0_1_1.py
clean/updates/versions/version.py
clean-0.1.3.dist-info/DESCRIPTION.rst
clean-0.1.3.dist-info/METADATA
clean-0.1.3.dist-info/RECORD
clean-0.1.3.dist-info/WHEEL
clean-0.1.3.dist-info/entry_points.txt
clean-0.1.3.dist-info/metadata.json
clean-0.1.3.dist-info/top_level.txt
tests/__init__.py
tests/test_cli.py
tests/test_config.py
