Metadata-Version: 2.0
Name: clean
Version: 0.1.3
Summary: clean: Command line file sorter(mover)
Home-page: https://github.com/HibikineKage/clean
Author: Hibikine Kage
Author-email: goodsmile314159@gmail.com
License: MIT
Platform: UNKNOWN
